librtmp/amf.py
librtmp/aval.py
librtmp/compat.py
librtmp/exceptions.py
librtmp/ffi.py
librtmp/logging.py
librtmp/packet.py
librtmp/rtmp.py
librtmp/stream.py
librtmp/utils.py
librtmp/_librtmp.pyd
librtmp/__init__.py
python_librtmp-0.3.0.dist-info/DESCRIPTION.rst
python_librtmp-0.3.0.dist-info/METADATA
python_librtmp-0.3.0.dist-info/metadata.json
python_librtmp-0.3.0.dist-info/RECORD
python_librtmp-0.3.0.dist-info/top_level.txt
python_librtmp-0.3.0.dist-info/WHEEL
