Metadata-Version: 2.0
Name: python-librtmp
Version: 0.3.0
Summary: Python bindings for librtmp, built with cffi
Home-page: https://github.com/chrippa/python-librtmp
Author: Christopher Rosell
Author-email: chrippa@tanuki.se
License: Simplified BSD
Keywords: python-librtmp
Platform: UNKNOWN
Classifier: Development Status :: 2 - Beta
Classifier: Intended Audience :: Developers
Classifier: License :: OSI Approved :: BSD License
Classifier: Natural Language :: English
Classifier: Programming Language :: Python :: 2
Classifier: Programming Language :: Python :: 2.6
Classifier: Programming Language :: Python :: 2.7
Classifier: Programming Language :: Python :: 3
Classifier: Programming Language :: Python :: 3.3
Classifier: Programming Language :: Python :: 3.4
Requires-Dist: cffi (>=1.0.1)
